PyQt5/Qt5/qsci/api/python/PyQtPurchasing.api
PyQt5/QtPurchasing.pyd
PyQt5/QtPurchasing.pyi
PyQt5/bindings/QtPurchasing/QtPurchasing.toml
PyQt5/bindings/QtPurchasing/QtPurchasingmod.sip
PyQt5/bindings/QtPurchasing/qinappproduct.sip
PyQt5/bindings/QtPurchasing/qinappstore.sip
PyQt5/bindings/QtPurchasing/qinapptransaction.sip
PyQt5/bindings/QtPurchasing/qtpurchasingversion.sip
PyQtPurchasing-5.15.6.dist-info/WHEEL
PyQtPurchasing-5.15.6.dist-info/METADATA
PyQtPurchasing-5.15.6.dist-info/RECORD
