Metadata-Version: 2.1
Name: PyQtPurchasing
Version: 5.15.6
Requires-Python: >=3.8
Summary: Python bindings for the Qt Purchasing library
Project-Url: homepage, https://www.riverbankcomputing.com/software/pyqtpurchasing/
Requires-Dist: PyQt5-sip (>=12.13, <13)
Requires-Dist: PyQtPurchasing-Qt5 (>=5.15.0, <5.16.0)
Requires-Dist: PyQt5 (>=5.15.4)
License: GPL v3
Author-Email: Riverbank Computing Limited <info@riverbankcomputing.com>
